{
  "tilesurl": "./static/tiles/rtrolley_{f}.png",
  "hotspots": [
    {
      "title": "Escenario NUEVO",
      "id": 1,
      "position": {
          "yaw": -0.018323469674399462,
          "pitch": -0.11348123666542875
        }
    },
    {
      "title": "Puerta Derecha",
      "id": 2,
      "position": {
          "yaw": 0.39971627640939467,
          "pitch": 0.08876564168822298
        }
    },
    {
      "title": "Camarin",
      "id": 3,
      "position": {
          "yaw": 1.8,
          "pitch": 20
        }
    }
  ],
  "pages": {
    "about": "Sed porta laoreet ligula euismod condimentum. Suspendisse porta hendrerit turpis tempus mattis. Nullam non dictum libero. Ut placerat dignissim efficitur. Ut felis ex, gravida in maximus vitae, sagittis sed nibh. Vestibulum vel finibus velit. Vestibulum in turpis dolor. Nullam fringilla sed ligula eu ullamcorper. Quisque efficitur, erat eget imperdiet imperdiet, felis velit porta lacus, consequat congue libero nibh id augue. Pellentesque accumsan ornare commodo. Sed ut augue at ipsum ultrices viverra vel non enim. In at tortor sed arcu consectetur pellentesque ut non eros. Vestibulum ante ipsum primis in faucibus orci luctus et ultrices posuere cubilia Curae; Mauris vitae bibendum nisi, sit amet sodales risus. Proin pulvinar purus et tristique imperdiet. Phasellus rhoncus est nulla, at varius turpis pellentesque quis. "
  }
}
